anyserver/__init__.py
anyserver/config.py
anyserver/encoder.py
anyserver/router.py
anyserver/server.py
anyserver/templates.py
anyserver/encoders/base.py
anyserver/encoders/csv.py
anyserver/encoders/html.py
anyserver/encoders/json.py
anyserver/encoders/text.py
anyserver/encoders/yaml.py
anyserver/servers/abstract.py
anyserver/servers/fastapi.py
anyserver/servers/flask.py
anyserver/servers/simple.py
anyserver-0.2.0.dist-info/LICENSE.txt
anyserver-0.2.0.dist-info/METADATA
anyserver-0.2.0.dist-info/WHEEL
anyserver-0.2.0.dist-info/top_level.txt
anyserver-0.2.0.dist-info/RECORD
