Metadata-Version: 2.1
Name: anyserver
Version: 0.2.0
Summary: Simple and generic python web server and utils
Home-page: https://github.com/JohnnyBeProgramming/anyserver.py
Download-URL: https://github.com/JohnnyBeProgramming/anyserver.py/archive/refs/tags/0.2.0.tar.gz
Author: Club404
Author-email: info@club404.io
License: MIT
Keywords: simple,http,server
Classifier: Development Status :: 3 - Alpha
Classifier: Intended Audience :: Developers
Classifier: Topic :: Software Development :: Build Tools
Classifier: License :: OSI Approved :: MIT License
Classifier: Programming Language :: Python :: 3
Classifier: Programming Language :: Python :: 3.4
Classifier: Programming Language :: Python :: 3.5
Classifier: Programming Language :: Python :: 3.6
License-File: LICENSE.txt
